consumers_core/__init__.py
consumers_core/common.py
consumers_core/consumer.py
consumers_core/cm/__init__.py
consumers_core/cm/commandLine.py
consumers_core/cm/main.py
tests/__init__.py
tests/context.py
tests/test_common.py
ni_consumers_core-0.2.14.dist-info/LICENSE
ni_consumers_core-0.2.14.dist-info/METADATA
ni_consumers_core-0.2.14.dist-info/WHEEL
ni_consumers_core-0.2.14.dist-info/entry_points.txt
ni_consumers_core-0.2.14.dist-info/top_level.txt
ni_consumers_core-0.2.14.dist-info/RECORD
