Metadata-Version: 2.1
Name: ni-consumers-core
Version: 0.2.14
Summary: UNKNOWN
Home-page: https://github.com/pypa/sampleproject
Author: Primael Bruant
Author-email: primael.bruant@gmail.com
License: UNKNOWN
Platform: UNKNOWN
Classifier: Programming Language :: Python :: 3
Classifier: License :: OSI Approved :: MIT License
Classifier: Operating System :: OS Independent
Requires-Python: >=3.6
Requires-Dist: pika (==1.1.0)
Requires-Dist: requests (==2.23.0)
Requires-Dist: coloredlogs (==14.0)
Requires-Dist: click (==7.1.2)
Requires-Dist: ni-logging-utils (==0.0.3)
